src/__init__.py
pulsewidth-1.0.4.dist-info/LICENSE
pulsewidth-1.0.4.dist-info/METADATA
pulsewidth-1.0.4.dist-info/WHEEL
pulsewidth-1.0.4.dist-info/top_level.txt
pulsewidth-1.0.4.dist-info/RECORD
